PyPlaybook/Port_Range_VLAN_Changes.py
PyPlaybook/PyPlaybook.py
PyPlaybook/__init__.py
PyPlaybook-0.0.11.dist-info/LICENSE
PyPlaybook-0.0.11.dist-info/METADATA
PyPlaybook-0.0.11.dist-info/WHEEL
PyPlaybook-0.0.11.dist-info/top_level.txt
PyPlaybook-0.0.11.dist-info/RECORD
