Metadata-Version: 2.1
Name: PyPlaybook
Version: 0.0.11
Summary: SSH/Telnet/playbook/automation tool/configuration tool/push commands from excel
Home-page: https://github.com/dmorfe/playbook_orchestration
Author: David Morfe
Author-email: cybercomprepair@gmail.com
License: MIT
Classifier: Programming Language :: Python :: 3
Classifier: License :: OSI Approved :: MIT License
Classifier: Operating System :: OS Independent
License-File: LICENSE
Requires-Dist: netmiko
Requires-Dist: pandas
Requires-Dist: xlrd
Requires-Dist: openpyxl
